zdppy_mcrud/__init__.py
zdppy_mcrud/db/__init__.py
zdppy_mcrud/db/add.py
zdppy_mcrud/db/base.py
zdppy_mcrud/db/database.py
zdppy_mcrud/db/db.py
zdppy_mcrud/db/delete.py
zdppy_mcrud/db/env.py
zdppy_mcrud/db/exceptions.py
zdppy_mcrud/db/get.py
zdppy_mcrud/db/has.py
zdppy_mcrud/db/update.py
zdppy_mcrud/sec/__init__.py
zdppy_mcrud/sec/column.py
zdppy_mcrud/sec/order.py
zdppy_mcrud/sec/sid.py
zdppy_mcrud/sec/str.py
zdppy_mcrud/sql/__init__.py
zdppy_mcrud/sql/alter.py
zdppy_mcrud/sql/delete.py
zdppy_mcrud/sql/get.py
zdppy_mcrud/sql/sql.py
zdppy_mcrud/sql/update.py
zdppy_mcrud/table/__init__.py
zdppy_mcrud-0.1.0.dist-info/LICENSE
zdppy_mcrud-0.1.0.dist-info/METADATA
zdppy_mcrud-0.1.0.dist-info/WHEEL
zdppy_mcrud-0.1.0.dist-info/RECORD
