Metadata-Version: 2.1
Name: zdppy-mcrud
Version: 0.1.0
Summary: Python操作MySQL常用增删改查操作的低代码框架
Author: 张大鹏
Author-email: 1156956636@qq.com
Requires-Python: >=3.8,<4.0
Classifier: Programming Language :: Python :: 3
Classifier: Programming Language :: Python :: 3.8
Classifier: Programming Language :: Python :: 3.9
Classifier: Programming Language :: Python :: 3.10
Classifier: Programming Language :: Python :: 3.11
Classifier: Programming Language :: Python :: 3.12
